{
  "movie_id": "Paperman [2012, BDRemux 1080p]",
  "movie_path": "E:\\film_oral\\Paperman (2012)\\Paperman [2012, BDRemux 1080p].mkv",
  "subtitle_path": "E:\\film_oral\\Paperman (2012)\\Paperman [2012, BDRemux 1080p].en.srt",
  "intervalle_secondes": 15,
  "nombre_intervalles": 27,
  "dossier_videos": "analyse\\videos\\Paperman [2012, BDRemux 1080p]",
  "date_traitement": "2026-03-26T20:22:46.165462",
  "stats_extraction": {
    "total": 27,
    "reussis": 27,
    "echecs": 0,
    "timeouts": 4,
    "gpu_errors": 0,
    "cpu_fallbacks": 4
  },
  "intervalles": [
    {
      "intervalle_index": 0,
      "intervalle_debut": 0,
      "intervalle_fin": 15,
      "timecode_debut_extrait": 0,
      "timecode_fin_extrait": 15,
      "video_path": "analyse\\videos\\Paperman [2012, BDRemux 1080p]\\interval_0000_time_0.00s-15.00s.mp4",
      "nombre_sous_titres": 3,
      "sous_titres": [
        {
          "index": "﻿1",
          "start": 1.5430000000000001,
          "end": 2.795,
          "text": "(WHISTLING)"
        },
        {
          "index": 2,
          "start": 2.92,
          "end": 4.763,
          "text": "(PIANO MUSIC PLAYING)"
        },
        {
          "index": 3,
          "start": 11.261,
          "end": 13.013,
          "text": "(TRAIN APPROACHING)"
        }
      ],
      "failed_attempts": 0
    },
    {
      "intervalle_index": 1,
      "intervalle_debut": 15,
      "intervalle_fin": 30,
      "timecode_debut_extrait": 15,
      "timecode_fin_extrait": 30,
      "video_path": "analyse\\videos\\Paperman [2012, BDRemux 1080p]\\interval_0001_time_15.00s-30.00s.mp4",
      "nombre_sous_titres": 1,
      "sous_titres": [
        {
          "index": 4,
          "start": 23.398,
          "end": 25.446,
          "text": "(MELODIOUS MUSIC PLAYING)"
        }
      ],
      "failed_attempts": 0
    },
    {
      "intervalle_index": 2,
      "intervalle_debut": 30,
      "intervalle_fin": 45,
      "timecode_debut_extrait": 30,
      "timecode_fin_extrait": 45,
      "video_path": "analyse\\videos\\Paperman [2012, BDRemux 1080p]\\interval_0002_time_30.00s-45.00s.mp4",
      "nombre_sous_titres": 1,
      "sous_titres": [
        {
          "index": 5,
          "start": 34.451,
          "end": 35.623,
          "text": "(TRAIN APPROACHING)"
        }
      ],
      "failed_attempts": 0
    },
    {
      "intervalle_index": 3,
      "intervalle_debut": 45,
      "intervalle_fin": 60,
      "timecode_debut_extrait": 45,
      "timecode_fin_extrait": 60,
      "video_path": "analyse\\videos\\Paperman [2012, BDRemux 1080p]\\interval_0003_time_45.00s-60.00s.mp4",
      "nombre_sous_titres": 3,
      "sous_titres": [
        {
          "index": 6,
          "start": 46.964,
          "end": 48.056,
          "text": "(CHUCKLES)"
        },
        {
          "index": 7,
          "start": 50.968,
          "end": 51.969,
          "text": "(CHUCKLES)"
        },
        {
          "index": 8,
          "start": 52.052,
          "end": 53.053,
          "text": "(BELL RINGS)"
        }
      ],
      "failed_attempts": 0
    },
    {
      "intervalle_index": 4,
      "intervalle_debut": 60,
      "intervalle_fin": 75,
      "timecode_debut_extrait": 60,
      "timecode_fin_extrait": 75,
      "video_path": "analyse\\videos\\Paperman [2012, BDRemux 1080p]\\interval_0004_time_60.00s-75.00s.mp4",
      "nombre_sous_titres": 1,
      "sous_titres": [
        {
          "index": 9,
          "start": 70.988,
          "end": 72.786,
          "text": "(TYPEWRITERS CLACKING)"
        }
      ],
      "failed_attempts": 0
    },
    {
      "intervalle_index": 5,
      "intervalle_debut": 75,
      "intervalle_fin": 90,
      "timecode_debut_extrait": 75,
      "timecode_fin_extrait": 90,
      "video_path": "analyse\\videos\\Paperman [2012, BDRemux 1080p]\\interval_0005_time_75.00s-90.00s.mp4",
      "nombre_sous_titres": 1,
      "sous_titres": [
        {
          "index": 10,
          "start": 80.455,
          "end": 81.707,
          "text": "(WIND BLOWING)"
        }
      ],
      "failed_attempts": 0
    },
    {
      "intervalle_index": 6,
      "intervalle_debut": 90,
      "intervalle_fin": 105,
      "timecode_debut_extrait": 90,
      "timecode_fin_extrait": 105,
      "video_path": "analyse\\videos\\Paperman [2012, BDRemux 1080p]\\interval_0006_time_90.00s-105.00s.mp4",
      "nombre_sous_titres": 2,
      "sous_titres": [
        {
          "index": 11,
          "start": 93.26,
          "end": 95.103,
          "text": "(MELODIOUS MUSIC PLAYING)"
        },
        {
          "index": 12,
          "start": 98.682,
          "end": 99.729,
          "text": "(MAN CLEARS THROAT)"
        }
      ],
      "failed_attempts": 0
    },
    {
      "intervalle_index": 7,
      "intervalle_debut": 105,
      "intervalle_fin": 120,
      "timecode_debut_extrait": 105,
      "timecode_fin_extrait": 120,
      "video_path": "analyse\\videos\\Paperman [2012, BDRemux 1080p]\\interval_0007_time_105.00s-120.00s.mp4",
      "nombre_sous_titres": 1,
      "sous_titres": [
        {
          "index": 13,
          "start": 108.859,
          "end": 110.031,
          "text": "(MUSIC CONTINUES)"
        }
      ],
      "failed_attempts": 0
    },
    {
      "intervalle_index": 8,
      "intervalle_debut": 120,
      "intervalle_fin": 135,
      "timecode_debut_extrait": 120,
      "timecode_fin_extrait": 135,
      "video_path": "analyse\\videos\\Paperman [2012, BDRemux 1080p]\\interval_0008_time_120.00s-135.00s.mp4",
      "nombre_sous_titres": 1,
      "sous_titres": [
        {
          "index": 14,
          "start": 122.289,
          "end": 123.541,
          "text": "(MELODIOUS MUSIC HEIGHTENS)"
        }
      ],
      "failed_attempts": 0
    },
    {
      "intervalle_index": 9,
      "intervalle_debut": 135,
      "intervalle_fin": 150,
      "timecode_debut_extrait": 135,
      "timecode_fin_extrait": 150,
      "video_path": "analyse\\videos\\Paperman [2012, BDRemux 1080p]\\interval_0009_time_135.00s-150.00s.mp4",
      "nombre_sous_titres": 2,
      "sous_titres": [
        {
          "index": 15,
          "start": 135.344,
          "end": 136.391,
          "text": "(MUSIC QUIETENS DOWNS)"
        },
        {
          "index": 16,
          "start": 140.724,
          "end": 142.271,
          "text": "(MELODIOUS MUSIC STARTS UP)"
        }
      ],
      "failed_attempts": 0
    },
    {
      "intervalle_index": 10,
      "intervalle_debut": 150,
      "intervalle_fin": 165,
      "timecode_debut_extrait": 150,
      "timecode_fin_extrait": 165,
      "video_path": "analyse\\videos\\Paperman [2012, BDRemux 1080p]\\interval_0010_time_150.00s-165.00s.mp4",
      "nombre_sous_titres": 1,
      "sous_titres": [
        {
          "index": 17,
          "start": 155.405,
          "end": 156.406,
          "text": "(MUSIC CONTINUES)"
        }
      ],
      "failed_attempts": 0
    },
    {
      "intervalle_index": 11,
      "intervalle_debut": 165,
      "intervalle_fin": 180,
      "timecode_debut_extrait": 165,
      "timecode_fin_extrait": 180,
      "video_path": "analyse\\videos\\Paperman [2012, BDRemux 1080p]\\interval_0011_time_165.00s-180.00s.mp4",
      "nombre_sous_titres": 2,
      "sous_titres": [
        {
          "index": 18,
          "start": 170.087,
          "end": 171.714,
          "text": "(CLATTERS LOUDLY) (MUSIC STOPS PLAYING)"
        },
        {
          "index": 19,
          "start": 179.346,
          "end": 180.723,
          "text": "(WIND BLOWING)"
        }
      ],
      "failed_attempts": 0
    },
    {
      "intervalle_index": 12,
      "intervalle_debut": 180,
      "intervalle_fin": 195,
      "timecode_debut_extrait": 180,
      "timecode_fin_extrait": 195,
      "video_path": "analyse\\videos\\Paperman [2012, BDRemux 1080p]\\interval_0012_time_180.00s-195.00s.mp4",
      "nombre_sous_titres": 4,
      "sous_titres": [
        {
          "index": 20,
          "start": 182.599,
          "end": 183.976,
          "text": "(MELODIOUS MUSIC PLAYS SOFTLY)"
        },
        {
          "index": 21,
          "start": 187.062,
          "end": 188.109,
          "text": "(WIND WHISTLES)"
        },
        {
          "index": 22,
          "start": 188.188,
          "end": 189.189,
          "text": "(GASPS)"
        },
        {
          "index": 23,
          "start": 189.272,
          "end": 190.615,
          "text": "(GROANS)"
        }
      ],
      "failed_attempts": 0
    },
    {
      "intervalle_index": 13,
      "intervalle_debut": 195,
      "intervalle_fin": 210,
      "timecode_debut_extrait": 195,
      "timecode_fin_extrait": 210,
      "video_path": "analyse\\videos\\Paperman [2012, BDRemux 1080p]\\interval_0013_time_195.00s-210.00s.mp4",
      "nombre_sous_titres": 1,
      "sous_titres": [
        {
          "index": 24,
          "start": 196.613,
          "end": 197.705,
          "text": "(MUSIC CONTINUES)"
        }
      ],
      "failed_attempts": 0
    },
    {
      "intervalle_index": 14,
      "intervalle_debut": 210,
      "intervalle_fin": 225,
      "timecode_debut_extrait": 210,
      "timecode_fin_extrait": 225,
      "video_path": "analyse\\videos\\Paperman [2012, BDRemux 1080p]\\interval_0014_time_210.00s-225.00s.mp4",
      "nombre_sous_titres": 3,
      "sous_titres": [
        {
          "index": 25,
          "start": 212.838,
          "end": 214.681,
          "text": "(MELODIOUS MUSIC HEIGHTENS)"
        },
        {
          "index": 26,
          "start": 220.262,
          "end": 221.434,
          "text": "(TRAFFIC RUMBLING)"
        },
        {
          "index": 27,
          "start": 224.725,
          "end": 225.977,
          "text": "(MUSIC STOPS PLAYING)"
        }
      ],
      "failed_attempts": 0
    },
    {
      "intervalle_index": 15,
      "intervalle_debut": 225,
      "intervalle_fin": 240,
      "timecode_debut_extrait": 225,
      "timecode_fin_extrait": 240,
      "video_path": "analyse\\videos\\Paperman [2012, BDRemux 1080p]\\interval_0015_time_225.00s-240.00s.mp4",
      "nombre_sous_titres": 4,
      "sous_titres": [
        {
          "index": 28,
          "start": 226.268,
          "end": 227.36,
          "text": "(TIRES SCREECHING)"
        },
        {
          "index": 29,
          "start": 228.478,
          "end": 229.57,
          "text": "(HONKING)"
        },
        {
          "index": 30,
          "start": 230.647,
          "end": 231.899,
          "text": "(PANTING)"
        },
        {
          "index": 31,
          "start": 237.529,
          "end": 239.247,
          "text": "(MELODIOUS MUSIC PLAYS SOFTLY)"
        }
      ],
      "failed_attempts": 0
    },
    {
      "intervalle_index": 16,
      "intervalle_debut": 240,
      "intervalle_fin": 255,
      "timecode_debut_extrait": 240,
      "timecode_fin_extrait": 255,
      "video_path": "analyse\\videos\\Paperman [2012, BDRemux 1080p]\\interval_0016_time_240.00s-255.00s.mp4",
      "nombre_sous_titres": 1,
      "sous_titres": [
        {
          "index": 32,
          "start": 253.67,
          "end": 254.796,
          "text": "(MUSIC CONTINUES)"
        }
      ],
      "failed_attempts": 0
    },
    {
      "intervalle_index": 17,
      "intervalle_debut": 255,
      "intervalle_fin": 270,
      "timecode_debut_extrait": 255,
      "timecode_fin_extrait": 270,
      "video_path": "analyse\\videos\\Paperman [2012, BDRemux 1080p]\\interval_0017_time_255.00s-270.00s.mp4",
      "nombre_sous_titres": 1,
      "sous_titres": [
        {
          "index": 33,
          "start": 263.638,
          "end": 264.764,
          "text": "(MUSIC CONTINUES)"
        }
      ],
      "failed_attempts": 0
    },
    {
      "intervalle_index": 18,
      "intervalle_debut": 270,
      "intervalle_fin": 285,
      "timecode_debut_extrait": 270,
      "timecode_fin_extrait": 285,
      "video_path": "analyse\\videos\\Paperman [2012, BDRemux 1080p]\\interval_0018_time_270.00s-285.00s.mp4",
      "nombre_sous_titres": 2,
      "sous_titres": [
        {
          "index": 34,
          "start": 274.149,
          "end": 275.526,
          "text": "(MELODIOUS MUSIC QUICKENS)"
        },
        {
          "index": 35,
          "start": 276.109,
          "end": 277.11,
          "text": "(WIND BLOWING)"
        }
      ],
      "failed_attempts": 0
    },
    {
      "intervalle_index": 19,
      "intervalle_debut": 285,
      "intervalle_fin": 300,
      "timecode_debut_extrait": 285,
      "timecode_fin_extrait": 300,
      "video_path": "analyse\\videos\\Paperman [2012, BDRemux 1080p]\\interval_0019_time_285.00s-300.00s.mp4",
      "nombre_sous_titres": 1,
      "sous_titres": [
        {
          "index": 36,
          "start": 290.457,
          "end": 291.709,
          "text": "(MUSIC CONTINUES)"
        }
      ],
      "failed_attempts": 0
    },
    {
      "intervalle_index": 20,
      "intervalle_debut": 300,
      "intervalle_fin": 315,
      "timecode_debut_extrait": 300,
      "timecode_fin_extrait": 315,
      "video_path": "analyse\\videos\\Paperman [2012, BDRemux 1080p]\\interval_0020_time_300.00s-315.00s.mp4",
      "nombre_sous_titres": 1,
      "sous_titres": [
        {
          "index": 37,
          "start": 300.675,
          "end": 301.927,
          "text": "(BRAKES SCREECHING)"
        }
      ],
      "failed_attempts": 0
    },
    {
      "intervalle_index": 21,
      "intervalle_debut": 315,
      "intervalle_fin": 330,
      "timecode_debut_extrait": 315,
      "timecode_fin_extrait": 330,
      "video_path": "analyse\\videos\\Paperman [2012, BDRemux 1080p]\\interval_0021_time_315.00s-330.00s.mp4",
      "nombre_sous_titres": 1,
      "sous_titres": [
        {
          "index": 38,
          "start": 316.233,
          "end": 318.361,
          "text": "(MELODIOUS MUSIC HEIGHTENS)"
        }
      ],
      "failed_attempts": 0
    },
    {
      "intervalle_index": 22,
      "intervalle_debut": 330,
      "intervalle_fin": 345,
      "timecode_debut_extrait": 330,
      "timecode_fin_extrait": 345,
      "video_path": "analyse\\videos\\Paperman [2012, BDRemux 1080p]\\interval_0022_time_330.00s-345.00s.mp4",
      "nombre_sous_titres": 1,
      "sous_titres": [
        {
          "index": 39,
          "start": 339.256,
          "end": 340.473,
          "text": "(MUSIC CONTINUES)"
        }
      ],
      "failed_attempts": 0
    },
    {
      "intervalle_index": 23,
      "intervalle_debut": 345,
      "intervalle_fin": 360,
      "timecode_debut_extrait": 345,
      "timecode_fin_extrait": 360,
      "video_path": "analyse\\videos\\Paperman [2012, BDRemux 1080p]\\interval_0023_time_345.00s-360.00s.mp4",
      "nombre_sous_titres": 3,
      "sous_titres": [
        {
          "index": 40,
          "start": 346.263,
          "end": 347.606,
          "text": "(BELL RINGS)"
        },
        {
          "index": 41,
          "start": 351.643,
          "end": 353.52,
          "text": "(MUSIC QUIETENS DOWNS)"
        },
        {
          "index": 42,
          "start": 358.483,
          "end": 359.484,
          "text": "(WIND BLOWING)"
        }
      ],
      "failed_attempts": 0
    },
    {
      "intervalle_index": 24,
      "intervalle_debut": 360,
      "intervalle_fin": 375,
      "timecode_debut_extrait": 360,
      "timecode_fin_extrait": 375,
      "video_path": "analyse\\videos\\Paperman [2012, BDRemux 1080p]\\interval_0024_time_360.00s-375.00s.mp4",
      "nombre_sous_titres": 2,
      "sous_titres": [
        {
          "index": 43,
          "start": 366.032,
          "end": 367.454,
          "text": "(ROMANTIC MUSIC PLAYING)"
        },
        {
          "index": 44,
          "start": 372.455,
          "end": 373.923,
          "text": "(MUSIC CONTINUES)"
        }
      ],
      "failed_attempts": 0
    },
    {
      "intervalle_index": 25,
      "intervalle_debut": 375,
      "intervalle_fin": 390,
      "timecode_debut_extrait": 375,
      "timecode_fin_extrait": 390,
      "video_path": "analyse\\videos\\Paperman [2012, BDRemux 1080p]\\interval_0025_time_375.00s-390.00s.mp4",
      "nombre_sous_titres": 0,
      "sous_titres": [],
      "failed_attempts": 0
    },
    {
      "intervalle_index": 26,
      "intervalle_debut": 390,
      "intervalle_fin": 394.496,
      "timecode_debut_extrait": 390,
      "timecode_fin_extrait": 394.496,
      "video_path": "analyse\\videos\\Paperman [2012, BDRemux 1080p]\\interval_0026_time_390.00s-394.50s.mp4",
      "nombre_sous_titres": 0,
      "sous_titres": [],
      "failed_attempts": 0
    }
  ]
}